replay_highlights_stream/__init__.py
replay_highlights_stream/initConfig.py
replay_highlights_stream/logger.py
replay_highlights_stream/newReplay.py
Replay_Highlights_Stream-2023613.14.58.dist-info/METADATA
Replay_Highlights_Stream-2023613.14.58.dist-info/WHEEL
Replay_Highlights_Stream-2023613.14.58.dist-info/top_level.txt
Replay_Highlights_Stream-2023613.14.58.dist-info/RECORD
