Metadata-Version: 2.1
Name: Replay-Highlights-Stream
Version: 2023613.14.58
Summary: Replay de las mejores jugadas de capturadas por apps de Overwolf
Home-page: https://github.com/Alderan-Smile/Replay-Highlights-Stream
Author: Oliver Consterla Araya
Author-email: oliver_consterla@yahoo.cl
Classifier: Programming Language :: Python :: 3
Classifier: License :: OSI Approved :: MIT License
Classifier: Operating System :: OS Independent
Requires-Python: >=3.6
Requires-Dist: watchdog
Requires-Dist: moviepy
Requires-Dist: pyglet
Requires-Dist: pydub
